statopy/__init__.py
statopy/skeleton.py
statopy/statopy.py
statopy-0.0.2.dist-info/AUTHORS.rst
statopy-0.0.2.dist-info/LICENSE.txt
statopy-0.0.2.dist-info/METADATA
statopy-0.0.2.dist-info/WHEEL
statopy-0.0.2.dist-info/top_level.txt
statopy-0.0.2.dist-info/RECORD
