Metadata-Version: 2.1
Name: statopy
Version: 0.0.2
Summary: Statistics and Probability modules
Home-page: https://github.com/mmiguel6288code/statopy
Author: Matthew Miguel
Author-email: mmiguel6288@gmail.com
License: mit
Project-URL: Documentation, https://github.com/mmiguel6288code/statopy
Platform: any
Classifier: Development Status :: 4 - Beta
Classifier: Programming Language :: Python
Requires-Dist: numpy
Requires-Dist: scipy
Requires-Dist: matplotlib
Provides-Extra: testing
Requires-Dist: pytest ; extra == 'testing'
Requires-Dist: pytest-cov ; extra == 'testing'
